{
  "tasks": [
    {
      "id": "123e4567-e89b-12d3-a456-426614174010",
      "title": "Test useTasks hook",
      "description": "Log and inspect the behavior of the hook before UI integration.",
      "assignee": {
        "name": "Michael",
        "avatar": "https://www.rockstargames.com/img/global/downloads/buddyiconsconavatars/v_hunt_m_256x256.jpg"
      },
      "reportTo": "Self",
      "dueDate": "2025-07-15",
      "priority": "low",
      "status": "done",
      "subtasks": [
        {
          "id": "234e5678-e89b-12d3-a456-426614174011",
          "title": "Create fake task data",
          "done": false
        },
        {
          "id": "345e6789-e89b-12d3-a456-426614174012",
          "title": "Call hook from test file",
          "done": true
        }
      ],
      "comments": [
        {
          "id": "456e7890-e89b-12d3-a456-426614174013",
          "text": "Done and logged correctly",
          "author": "Abdelrahman"
        }
      ]
    },
    {
      "id": "901e2345-e89b-12d3-a456-426614174018",
      "title": "Create modal for task editing",
      "description": "Allow user to view, edit, and update tasks in a modal.",
      "assignee": {
        "name": "Franklin",
        "avatar": "https://www.rockstargames.com/img/global/downloads/buddyiconsconavatars/v_hunt_f_256x256.jpg"
      },
      "reportTo": "Mentor",
      "dueDate": "2025-07-25",
      "priority": "high",
      "status": "todo",
      "subtasks": [
        {
          "id": "012e3456-e89b-12d3-a456-426614174019",
          "title": "Build modal shell",
          "done": true
        },
        {
          "id": "123e4567-e89b-12d3-a456-426614174020",
          "title": "Add form inputs",
          "done": true
        },
        {
          "id": "234e5678-e89b-12d3-a456-426614174021",
          "title": "Save edited task",
          "done": false
        }
      ],
      "comments": []
    },
    {
      "id": "345e6789-e89b-12d3-a456-426614174022",
      "title": "Implement task board view",
      "description": "Display tasks grouped by status in cards (To-Do, In Progress, Done).",
      "assignee": {
        "name": "Trevor",
        "avatar": "https://www.rockstargames.com/img/global/downloads/buddyiconsconavatars/v_hunt_t_256x256.jpg"
      },
      "reportTo": "Mentor",
      "dueDate": "2025-07-23",
      "priority": "medium",
      "status": "in-progress",
      "subtasks": [],
      "comments": [
        {
          "id": "678e9012-e89b-12d3-a456-426614174025",
          "text": "Try adding drag-and-drop later",
          "author": "Mentor"
        }
      ]
    }
  ]
}
